COPYRIGHT
MANIFEST.in
setup.cfg
setup.py
docs/Makefile
docs/api_docs.rst
docs/conf.py
docs/index.rst
docs/make.bat
unstats/__init__.py
unstats/cofog.py
unstats/data/cofog/COFOG99_DE.xml
unstats/data/cofog/COFOG99_EN.xml
unstats/data/cofog/COFOG99_FR.xml
unstats_rdf.egg-info/PKG-INFO
unstats_rdf.egg-info/SOURCES.txt
unstats_rdf.egg-info/datapkg_index.txt
unstats_rdf.egg-info/dependency_links.txt
unstats_rdf.egg-info/entry_points.txt
unstats_rdf.egg-info/not-zip-safe
unstats_rdf.egg-info/requires.txt
unstats_rdf.egg-info/top_level.txt