Metadata-Version: 1.0
Name: unstats-rdf
Version: 0.2
Summary: RDF API for UN Statistical Division Data
Home-page: http://pypi.python.org/pypi/unstats_rdf_data
Author: Open Knowledge Foundation
Author-email: okfn-help@lists.okfn.org
License: BSD
Keywords: unstats rdf
Platform: UNKNOWN
Classifier: Development Status :: 3 - Alpha
Classifier: Environment :: Console
Classifier: Environment :: Web Environment
Classifier: Framework :: Paste
Classifier: Intended Audience :: Developers
Classifier: Intended Audience :: Information Technology
Classifier: License :: OSI Approved :: GNU Affero General Public License v3
Classifier: Operating System :: POSIX
Classifier: Programming Language :: Python :: 2.6
Classifier: Topic :: Internet
Classifier: Topic :: Software Development :: Libraries :: Python Modules
